rtl/alu.sv
module alu (
    input  logic [31:0] a,
    input  logic [31:0] b,
    input  logic [3:0]  alu_op,
    output logic [31:0] result
);

    always_comb begin

        case (alu_op)

            // ADD
            4'b0000: result = a + b;


            // SUB
            4'b0001: result = a - b;

            // AND
            4'b0010: result = a & b;

            // OR
            4'b0011: result = a | b;

            // XOR
            4'b0100: result = a ^ b;

            // SLL
            4'b0101: result = a << b[4:0];

            // SRL
            4'b0110: result = a >> b[4:0];

            // SLT
            4'b0111: result = ($signed(a) < $signed(b)) ? 32'd1 : 32'd0;

            default: result = 32'b0;

        endcase

    end

endmodule

tb/alu_tb.sv
module alu_tb;

    logic [31:0] a;
    logic [31:0] b;
    logic [3:0]  alu_op;
    logic [31:0] result;

    alu dut (
        .a(a),
        .b(b),
        .alu_op(alu_op),
        .result(result)
    );

    task run_test(
        input logic [31:0] test_a,
        input logic [31:0] test_b,
        input logic [3:0]  test_operation,
        input logic [31:0] expected
    );
        begin
            a = test_a;
            b = test_b;
            alu_op = test_operation;

            #1;

            if (result === expected)
                $display("PASS: a=%h b=%h op=%b result=%h",
                            a, b, alu_op, result);
            else
                $display("FAIL: a=%h b=%h op=%b result=%h expected=%h",
                            a, b, alu_op, result, expected);
        end

    endtask

    initial begin

        $dumpfile("alu.vcd");
        $dumpvars(0, alu_tb);

        run_test(32'd10, 32'd7, 4'b0000, 32'd17);
        run_test(32'd10, 32'd7, 4'b0001, 32'd3);

        run_test(
            32'h000000FF,
            32'h0000000F,
            4'b0010,
            32'h0000000F
        );

        run_test(
            32'h000000F0,
            32'h0000000F,
            4'b0011,
            32'h000000FF
        );

        run_test(
            32'h000000FF,
            32'h0000000F,
            4'b0100,
            32'h000000F0
        );

        run_test(32'd4,  32'd2, 4'b0101, 32'd16);
        run_test(32'd16, 32'd2, 4'b0110, 32'd4);

        // -5 < 3
        run_test(
            32'hFFFFFFFB,
            32'd3,
            4'b0111,
            32'd1
        );
            // 0 + 0
        run_test(32'd0, 32'd0, 4'b0000, 32'd0);

        // Overflow/wraparound
        run_test(32'hFFFFFFFF, 32'd1, 4'b0000, 32'd0);

        // Equal values: 5 < 5 should be false
        run_test(32'd5, 32'd5, 4'b0111, 32'd0);

        // Positive < negative should be false
        run_test(32'd3, 32'hFFFFFFFB, 4'b0111, 32'd0);

        // Shift by 0
        run_test(32'd15, 32'd0, 4'b0101, 32'd15);

        // Shift by 31
        run_test(32'd1, 32'd31, 4'b0101, 32'h80000000);

        $finish;

    end

endmodule

alu.vcd
$version Generated by VerilatedVcd $end
$timescale 1ps $end
 $scope module $rootio $end
 $upscope $end
 $scope module alu_tb $end
  $var wire 32 # a [31:0] $end
  $var wire 32 $ b [31:0] $end
  $var wire 4 % alu_op [3:0] $end
  $var wire 32 & result [31:0] $end
  $scope module dut $end
   $var wire 32 # a [31:0] $end
   $var wire 32 $ b [31:0] $end
   $var wire 4 % alu_op [3:0] $end
   $var wire 32 & result [31:0] $end
  $upscope $end
 $upscope $end
$enddefinitions $end


#0
b00000000000000000000000000001010 #
b00000000000000000000000000000111 $
b0000 %
b00000000000000000000000000010001 &
#1
b0001 %
b00000000000000000000000000000011 &
#2
b00000000000000000000000011111111 #
b00000000000000000000000000001111 $
b0010 %
b00000000000000000000000000001111 &
#3
b00000000000000000000000011110000 #
b0011 %
b00000000000000000000000011111111 &
#4
b00000000000000000000000011111111 #
b0100 %
b00000000000000000000000011110000 &
#5
b00000000000000000000000000000100 #
b00000000000000000000000000000010 $
b0101 %
b00000000000000000000000000010000 &
#6
b00000000000000000000000000010000 #
b0110 %
b00000000000000000000000000000100 &
#7
b11111111111111111111111111111011 #
b00000000000000000000000000000011 $
b0111 %
b00000000000000000000000000000001 &
#8
b00000000000000000000000000000000 #
b00000000000000000000000000000000 $
b0000 %
b00000000000000000000000000000000 &
#9
b11111111111111111111111111111111 #
b00000000000000000000000000000001 $
#10
b00000000000000000000000000000101 #
b00000000000000000000000000000101 $
b0111 %
#11
b00000000000000000000000000000011 #
b11111111111111111111111111111011 $
#12
b00000000000000000000000000001111 #
b00000000000000000000000000000000 $
b0101 %
b00000000000000000000000000001111 &
#13
b00000000000000000000000000000001 #
b00000000000000000000000000011111 $
b10000000000000000000000000000000 &
